{
 "id": "2412026",
 "temporada": "2024",
 "competicion": "primerafeb",
 "grupo": "UNICO",
 "jornada": "Jornada 23(07/03/2025)",
 "equipoLocal": {
  "id": "950871",
  "nombre": "GRUPO ALEGA CANTABRIA"
 },
 "equipoVisitante": {
  "id": "950779",
  "nombre": "HLA ALICANTE"
 },
 "resultado": "83-72",
 "disputado": true,
 "descargado": "2026-07-20T18:02:59.202Z",
 "boxscore": {
  "local": [
   {
    "idJugador": "2533643",
    "titular": false,
    "dorsal": "0",
    "nombre": "ATENCIA SUAREZ, HANSEL GIOVANNY",
    "seg": 1085,
    "pt": 17,
    "t2": {
     "a": 3,
     "i": 4
    },
    "t3": {
     "a": 1,
     "i": 5
    },
    "tc": {
     "a": 4,
     "i": 9
    },
    "tl": {
     "a": 8,
     "i": 8
    },
    "ro": 0,
    "rd": 2,
    "rt": 2,
    "as": 4,
    "br": 0,
    "bp": 1,
    "tf": 0,
    "tco": 0,
    "mt": 0,
    "fc": 1,
    "fr": 4,
    "va": 20,
    "pm": 4
   },
   {
    "idJugador": "2650877",
    "titular": false,
    "dorsal": "3",
    "nombre": "VOYTSO, VLADYSLAV",
    "seg": 1073,
    "pt": 0,
    "t2": {
     "a": 0,
     "i": 1
    },
    "t3": {
     "a": 0,
     "i": 1
    },
    "tc": {
     "a": 0,
     "i": 2
    },
    "tl": {
     "a": 0,
     "i": 0
    },
    "ro": 0,
    "rd": 2,
    "rt": 2,
    "as": 0,
    "br": 0,
    "bp": 0,
    "tf": 1,
    "tco": 0,
    "mt": 0,
    "fc": 4,
    "fr": 0,
    "va": -3,
    "pm": 3
   },
   {
    "idJugador": "2650859",
    "titular": true,
    "dorsal": "5",
    "nombre": "LITTLESON, SPENCER PHILLIP",
    "seg": 1596,
    "pt": 13,
    "t2": {
     "a": 2,
     "i": 6
    },
    "t3": {
     "a": 3,
     "i": 6
    },
    "tc": {
     "a": 5,
     "i": 12
    },
    "tl": {
     "a": 0,
     "i": 0
    },
    "ro": 1,
    "rd": 2,
    "rt": 3,
    "as": 0,
    "br": 1,
    "bp": 0,
    "tf": 0,
    "tco": 0,
    "mt": 0,
    "fc": 2,
    "fr": 1,
    "va": 9,
    "pm": 11
   },
   {
    "idJugador": "2158313",
    "titular": true,
    "dorsal": "7",
    "nombre": "BULIC, MIRZA",
    "seg": 1186,
    "pt": 8,
    "t2": {
     "a": 3,
     "i": 9
    },
    "t3": {
     "a": 0,
     "i": 1
    },
    "tc": {
     "a": 3,
     "i": 10
    },
    "tl": {
     "a": 2,
     "i": 3
    },
    "ro": 3,
    "rd": 3,
    "rt": 6,
    "as": 3,
    "br": 0,
    "bp": 1,
    "tf": 0,
    "tco": 0,
    "mt": 0,
    "fc": 0,
    "fr": 2,
    "va": 10,
    "pm": 15
   },
   {
    "idJugador": "1821694",
    "titular": false,
    "dorsal": "9",
    "nombre": "MARTINEZ DIAZ, GERMAN",
    "seg": 804,
    "pt": 3,
    "t2": {
     "a": 0,
     "i": 0
    },
    "t3": {
     "a": 1,
     "i": 2
    },
    "tc": {
     "a": 1,
     "i": 2
    },
    "tl": {
     "a": 0,
     "i": 0
    },
    "ro": 1,
    "rd": 4,
    "rt": 5,
    "as": 3,
    "br": 0,
    "bp": 0,
    "tf": 0,
    "tco": 0,
    "mt": 0,
    "fc": 3,
    "fr": 0,
    "va": 7,
    "pm": 0
   },
   {
    "idJugador": "1007257",
    "titular": false,
    "dorsal": "10",
    "nombre": "VEGA MERAYO, JAVIER",
    "seg": 1214,
    "pt": 5,
    "t2": {
     "a": 1,
     "i": 3
    },
    "t3": {
     "a": 1,
     "i": 4
    },
    "tc": {
     "a": 2,
     "i": 7
    },
    "tl": {
     "a": 0,
     "i": 0
    },
    "ro": 1,
    "rd": 3,
    "rt": 4,
    "as": 1,
    "br": 0,
    "bp": 0,
    "tf": 0,
    "tco": 0,
    "mt": 0,
    "fc": 1,
    "fr": 0,
    "va": 4,
    "pm": -4
   },
   {
    "idJugador": "2334896",
    "titular": false,
    "dorsal": "15",
    "nombre": "BERCY, KEVIN RICHARD",
    "seg": 772,
    "pt": 6,
    "t2": {
     "a": 3,
     "i": 4
    },
    "t3": {
     "a": 0,
     "i": 0
    },
    "tc": {
     "a": 3,
     "i": 4
    },
    "tl": {
     "a": 0,
     "i": 0
    },
    "ro": 0,
    "rd": 0,
    "rt": 0,
    "as": 0,
    "br": 1,
    "bp": 0,
    "tf": 0,
    "tco": 0,
    "mt": 0,
    "fc": 2,
    "fr": 0,
    "va": 4,
    "pm": 5
   },
   {
    "idJugador": "2274998",
    "titular": true,
    "dorsal": "32",
    "nombre": "JOHNSON JR, REGINALD",
    "seg": 1356,
    "pt": 16,
    "t2": {
     "a": 3,
     "i": 4
    },
    "t3": {
     "a": 2,
     "i": 4
    },
    "tc": {
     "a": 5,
     "i": 8
    },
    "tl": {
     "a": 4,
     "i": 4
    },
    "ro": 0,
    "rd": 0,
    "rt": 0,
    "as": 4,
    "br": 1,
    "bp": 2,
    "tf": 0,
    "tco": 0,
    "mt": 0,
    "fc": 1,
    "fr": 3,
    "va": 18,
    "pm": 10
   },
   {
    "idJugador": "2446696",
    "titular": true,
    "dorsal": "34",
    "nombre": "KANDE KIELI, GARMINE",
    "seg": 1628,
    "pt": 8,
    "t2": {
     "a": 3,
     "i": 5
    },
    "t3": {
     "a": 0,
     "i": 0
    },
    "tc": {
     "a": 3,
     "i": 5
    },
    "tl": {
     "a": 2,
     "i": 2
    },
    "ro": 1,
    "rd": 1,
    "rt": 2,
    "as": 3,
    "br": 2,
    "bp": 2,
    "tf": 2,
    "tco": 0,
    "mt": 3,
    "fc": 0,
    "fr": 1,
    "va": 14,
    "pm": 6
   },
   {
    "idJugador": "2820728",
    "titular": true,
    "dorsal": "35",
    "nombre": "BELEMENE-DZABATOU, JUDICAËL ROMARIC",
    "seg": 1286,
    "pt": 7,
    "t2": {
     "a": 2,
     "i": 2
    },
    "t3": {
     "a": 1,
     "i": 2
    },
    "tc": {
     "a": 3,
     "i": 4
    },
    "tl": {
     "a": 0,
     "i": 0
    },
    "ro": 2,
    "rd": 3,
    "rt": 5,
    "as": 0,
    "br": 0,
    "bp": 0,
    "tf": 0,
    "tco": 0,
    "mt": 0,
    "fc": 4,
    "fr": 4,
    "va": 11,
    "pm": 5
   }
  ],
  "visitante": [
   {
    "idJugador": "2734617",
    "titular": true,
    "dorsal": "2",
    "nombre": "KING, JORDAN JAMES",
    "seg": 1877,
    "pt": 8,
    "t2": {
     "a": 2,
     "i": 5
    },
    "t3": {
     "a": 0,
     "i": 2
    },
    "tc": {
     "a": 2,
     "i": 7
    },
    "tl": {
     "a": 4,
     "i": 5
    },
    "ro": 0,
    "rd": 0,
    "rt": 0,
    "as": 1,
    "br": 0,
    "bp": 3,
    "tf": 0,
    "tco": 1,
    "mt": 0,
    "fc": 2,
    "fr": 3,
    "va": 1,
    "pm": -15
   },
   {
    "idJugador": "2787126",
    "titular": false,
    "dorsal": "4",
    "nombre": "CECCARDI, SEBASTIAN ARIS",
    "seg": 1320,
    "pt": 9,
    "t2": {
     "a": 0,
     "i": 1
    },
    "t3": {
     "a": 2,
     "i": 5
    },
    "tc": {
     "a": 2,
     "i": 6
    },
    "tl": {
     "a": 3,
     "i": 4
    },
    "ro": 0,
    "rd": 0,
    "rt": 0,
    "as": 2,
    "br": 0,
    "bp": 1,
    "tf": 0,
    "tco": 1,
    "mt": 0,
    "fc": 4,
    "fr": 2,
    "va": 3,
    "pm": 2
   },
   {
    "idJugador": "2734619",
    "titular": true,
    "dorsal": "8",
    "nombre": "MWEMA, JEAN MARC",
    "seg": 1285,
    "pt": 5,
    "t2": {
     "a": 1,
     "i": 1
    },
    "t3": {
     "a": 1,
     "i": 4
    },
    "tc": {
     "a": 2,
     "i": 5
    },
    "tl": {
     "a": 0,
     "i": 0
    },
    "ro": 1,
    "rd": 5,
    "rt": 6,
    "as": 2,
    "br": 0,
    "bp": 1,
    "tf": 0,
    "tco": 0,
    "mt": 0,
    "fc": 2,
    "fr": 0,
    "va": 7,
    "pm": -6
   },
   {
    "idJugador": "2734637",
    "titular": true,
    "dorsal": "11",
    "nombre": "MOUTE A BIDIAS, ROGER DUCLOS BERTIN",
    "seg": 1249,
    "pt": 10,
    "t2": {
     "a": 3,
     "i": 3
    },
    "t3": {
     "a": 0,
     "i": 2
    },
    "tc": {
     "a": 3,
     "i": 5
    },
    "tl": {
     "a": 4,
     "i": 4
    },
    "ro": 2,
    "rd": 3,
    "rt": 5,
    "as": 0,
    "br": 0,
    "bp": 2,
    "tf": 0,
    "tco": 0,
    "mt": 2,
    "fc": 3,
    "fr": 2,
    "va": 10,
    "pm": 0
   },
   {
    "idJugador": "1869762",
    "titular": false,
    "dorsal": "12",
    "nombre": "BRESSAN, GONZALO",
    "seg": 261,
    "pt": 0,
    "t2": {
     "a": 0,
     "i": 0
    },
    "t3": {
     "a": 0,
     "i": 0
    },
    "tc": {
     "a": 0,
     "i": 0
    },
    "tl": {
     "a": 0,
     "i": 0
    },
    "ro": 0,
    "rd": 0,
    "rt": 0,
    "as": 0,
    "br": 0,
    "bp": 0,
    "tf": 0,
    "tco": 0,
    "mt": 0,
    "fc": 0,
    "fr": 0,
    "va": 0,
    "pm": -8
   },
   {
    "idJugador": "1957913",
    "titular": true,
    "dorsal": "13",
    "nombre": "RODRIGUEZ JUAN, ADRIA",
    "seg": 450,
    "pt": 0,
    "t2": {
     "a": 0,
     "i": 0
    },
    "t3": {
     "a": 0,
     "i": 1
    },
    "tc": {
     "a": 0,
     "i": 1
    },
    "tl": {
     "a": 0,
     "i": 0
    },
    "ro": 0,
    "rd": 1,
    "rt": 1,
    "as": 0,
    "br": 0,
    "bp": 1,
    "tf": 0,
    "tco": 0,
    "mt": 0,
    "fc": 0,
    "fr": 0,
    "va": -1,
    "pm": -11
   },
   {
    "idJugador": "1535344",
    "titular": false,
    "dorsal": "15",
    "nombre": "ROSA POMPIDO, IGNACIO",
    "seg": 562,
    "pt": 3,
    "t2": {
     "a": 0,
     "i": 0
    },
    "t3": {
     "a": 1,
     "i": 1
    },
    "tc": {
     "a": 1,
     "i": 1
    },
    "tl": {
     "a": 0,
     "i": 0
    },
    "ro": 0,
    "rd": 3,
    "rt": 3,
    "as": 0,
    "br": 0,
    "bp": 0,
    "tf": 0,
    "tco": 0,
    "mt": 0,
    "fc": 1,
    "fr": 0,
    "va": 5,
    "pm": -5
   },
   {
    "idJugador": "2433482",
    "titular": true,
    "dorsal": "21",
    "nombre": "LARSEN, KEVIN RICKI",
    "seg": 1872,
    "pt": 13,
    "t2": {
     "a": 6,
     "i": 12
    },
    "t3": {
     "a": 0,
     "i": 2
    },
    "tc": {
     "a": 6,
     "i": 14
    },
    "tl": {
     "a": 1,
     "i": 2
    },
    "ro": 2,
    "rd": 3,
    "rt": 5,
    "as": 7,
    "br": 0,
    "bp": 0,
    "tf": 0,
    "tco": 0,
    "mt": 0,
    "fc": 0,
    "fr": 1,
    "va": 17,
    "pm": 0
   },
   {
    "idJugador": "2371555",
    "titular": false,
    "dorsal": "23",
    "nombre": "KACINAS, MINDAUGAS",
    "seg": 1199,
    "pt": 7,
    "t2": {
     "a": 1,
     "i": 2
    },
    "t3": {
     "a": 1,
     "i": 3
    },
    "tc": {
     "a": 2,
     "i": 5
    },
    "tl": {
     "a": 2,
     "i": 2
    },
    "ro": 2,
    "rd": 6,
    "rt": 8,
    "as": 0,
    "br": 0,
    "bp": 0,
    "tf": 0,
    "tco": 0,
    "mt": 0,
    "fc": 2,
    "fr": 4,
    "va": 14,
    "pm": -9
   },
   {
    "idJugador": "1124596",
    "titular": false,
    "dorsal": "25",
    "nombre": "LOPEZ LAZ, ALEJANDRO",
    "seg": 1004,
    "pt": 7,
    "t2": {
     "a": 3,
     "i": 3
    },
    "t3": {
     "a": 0,
     "i": 2
    },
    "tc": {
     "a": 3,
     "i": 5
    },
    "tl": {
     "a": 1,
     "i": 1
    },
    "ro": 0,
    "rd": 1,
    "rt": 1,
    "as": 0,
    "br": 0,
    "bp": 1,
    "tf": 0,
    "tco": 0,
    "mt": 0,
    "fc": 1,
    "fr": 2,
    "va": 6,
    "pm": 1
   },
   {
    "idJugador": "2446631",
    "titular": false,
    "dorsal": "44",
    "nombre": "ALI, PRINCE ADAMS",
    "seg": 921,
    "pt": 10,
    "t2": {
     "a": 3,
     "i": 9
    },
    "t3": {
     "a": 0,
     "i": 0
    },
    "tc": {
     "a": 3,
     "i": 9
    },
    "tl": {
     "a": 4,
     "i": 6
    },
    "ro": 0,
    "rd": 1,
    "rt": 1,
    "as": 1,
    "br": 0,
    "bp": 0,
    "tf": 0,
    "tco": 1,
    "mt": 0,
    "fc": 0,
    "fr": 4,
    "va": 8,
    "pm": -4
   }
  ],
  "cuartos": [
   {
    "periodo": "1º C",
    "local": 19,
    "visitante": 16
   },
   {
    "periodo": "2º C",
    "local": 21,
    "visitante": 16
   },
   {
    "periodo": "3º C",
    "local": 22,
    "visitante": 18
   },
   {
    "periodo": "4º C",
    "local": 21,
    "visitante": 22
   }
  ]
 }
}