{
 "id": "2486324",
 "temporada": "2025",
 "competicion": "primerafeb",
 "grupo": "UNICO",
 "jornada": "Jornada 8(14/11/2025)",
 "equipoLocal": {
  "id": "980004",
  "nombre": "LEYMA CORUÑA"
 },
 "equipoVisitante": {
  "id": "979769",
  "nombre": "MELILLA CIUDAD DEL DEPORTE"
 },
 "resultado": "101-89",
 "disputado": true,
 "descargado": "2026-07-20T13:21:02.432Z",
 "boxscore": {
  "local": [
   {
    "idJugador": "2557970",
    "titular": false,
    "dorsal": "0",
    "nombre": "CUEVAS SIMARRO, DIDAC",
    "seg": 1295,
    "pt": 12,
    "t2": {
     "a": 2,
     "i": 4
    },
    "t3": {
     "a": 2,
     "i": 7
    },
    "tc": {
     "a": 4,
     "i": 11
    },
    "tl": {
     "a": 2,
     "i": 4
    },
    "ro": 0,
    "rd": 6,
    "rt": 6,
    "as": 4,
    "br": 4,
    "bp": 1,
    "tf": 0,
    "tco": 0,
    "mt": 0,
    "fc": 0,
    "fr": 2,
    "va": 18,
    "pm": 13
   },
   {
    "idJugador": "2371535",
    "titular": true,
    "dorsal": "4",
    "nombre": "JORGENSEN, PAUL ANDERS",
    "seg": 1482,
    "pt": 14,
    "t2": {
     "a": 2,
     "i": 3
    },
    "t3": {
     "a": 2,
     "i": 6
    },
    "tc": {
     "a": 4,
     "i": 9
    },
    "tl": {
     "a": 4,
     "i": 5
    },
    "ro": 1,
    "rd": 2,
    "rt": 3,
    "as": 3,
    "br": 1,
    "bp": 2,
    "tf": 0,
    "tco": 0,
    "mt": 0,
    "fc": 2,
    "fr": 3,
    "va": 14,
    "pm": 5
   },
   {
    "idJugador": "1491674",
    "titular": true,
    "dorsal": "5",
    "nombre": "JOU COLL, GUILLEM",
    "seg": 1248,
    "pt": 6,
    "t2": {
     "a": 0,
     "i": 0
    },
    "t3": {
     "a": 2,
     "i": 5
    },
    "tc": {
     "a": 2,
     "i": 5
    },
    "tl": {
     "a": 0,
     "i": 0
    },
    "ro": 0,
    "rd": 3,
    "rt": 3,
    "as": 0,
    "br": 1,
    "bp": 0,
    "tf": 0,
    "tco": 0,
    "mt": 0,
    "fc": 2,
    "fr": 1,
    "va": 6,
    "pm": 1
   },
   {
    "idJugador": "2814191",
    "titular": false,
    "dorsal": "6",
    "nombre": "BRAZ, MACACHI BUANGA",
    "seg": 529,
    "pt": 4,
    "t2": {
     "a": 2,
     "i": 3
    },
    "t3": {
     "a": 0,
     "i": 0
    },
    "tc": {
     "a": 2,
     "i": 3
    },
    "tl": {
     "a": 0,
     "i": 0
    },
    "ro": 1,
    "rd": 0,
    "rt": 1,
    "as": 0,
    "br": 0,
    "bp": 0,
    "tf": 0,
    "tco": 0,
    "mt": 1,
    "fc": 2,
    "fr": 0,
    "va": 2,
    "pm": -3
   },
   {
    "idJugador": "2843861",
    "titular": true,
    "dorsal": "8",
    "nombre": "RADONCIC, DINO",
    "seg": 1277,
    "pt": 9,
    "t2": {
     "a": 3,
     "i": 5
    },
    "t3": {
     "a": 0,
     "i": 1
    },
    "tc": {
     "a": 3,
     "i": 6
    },
    "tl": {
     "a": 3,
     "i": 4
    },
    "ro": 2,
    "rd": 1,
    "rt": 3,
    "as": 2,
    "br": 2,
    "bp": 3,
    "tf": 0,
    "tco": 0,
    "mt": 0,
    "fc": 2,
    "fr": 2,
    "va": 9,
    "pm": 5
   },
   {
    "idJugador": "2644143",
    "titular": true,
    "dorsal": "9",
    "nombre": "DE SOUZA PACHECO, CAIO",
    "seg": 1354,
    "pt": 16,
    "t2": {
     "a": 2,
     "i": 4
    },
    "t3": {
     "a": 3,
     "i": 5
    },
    "tc": {
     "a": 5,
     "i": 9
    },
    "tl": {
     "a": 3,
     "i": 4
    },
    "ro": 1,
    "rd": 0,
    "rt": 1,
    "as": 5,
    "br": 0,
    "bp": 3,
    "tf": 0,
    "tco": 0,
    "mt": 0,
    "fc": 2,
    "fr": 5,
    "va": 17,
    "pm": 6
   },
   {
    "idJugador": "1848359",
    "titular": false,
    "dorsal": "21",
    "nombre": "DIOP GAYE, ILIMANE",
    "seg": 1102,
    "pt": 10,
    "t2": {
     "a": 2,
     "i": 2
    },
    "t3": {
     "a": 1,
     "i": 2
    },
    "tc": {
     "a": 3,
     "i": 4
    },
    "tl": {
     "a": 3,
     "i": 4
    },
    "ro": 2,
    "rd": 2,
    "rt": 4,
    "as": 0,
    "br": 0,
    "bp": 2,
    "tf": 2,
    "tco": 0,
    "mt": 2,
    "fc": 4,
    "fr": 4,
    "va": 12,
    "pm": 13
   },
   {
    "idJugador": "2452677",
    "titular": false,
    "dorsal": "24",
    "nombre": "CREMO, JOSEPH ROBERT",
    "seg": 1242,
    "pt": 11,
    "t2": {
     "a": 1,
     "i": 2
    },
    "t3": {
     "a": 3,
     "i": 4
    },
    "tc": {
     "a": 4,
     "i": 6
    },
    "tl": {
     "a": 0,
     "i": 0
    },
    "ro": 1,
    "rd": 1,
    "rt": 2,
    "as": 1,
    "br": 0,
    "bp": 4,
    "tf": 0,
    "tco": 0,
    "mt": 0,
    "fc": 2,
    "fr": 0,
    "va": 6,
    "pm": 9
   },
   {
    "idJugador": "2815798",
    "titular": true,
    "dorsal": "44",
    "nombre": "THIAM, ABDOU",
    "seg": 1298,
    "pt": 9,
    "t2": {
     "a": 3,
     "i": 5
    },
    "t3": {
     "a": 0,
     "i": 0
    },
    "tc": {
     "a": 3,
     "i": 5
    },
    "tl": {
     "a": 3,
     "i": 3
    },
    "ro": 1,
    "rd": 6,
    "rt": 7,
    "as": 1,
    "br": 0,
    "bp": 1,
    "tf": 0,
    "tco": 0,
    "mt": 1,
    "fc": 1,
    "fr": 3,
    "va": 16,
    "pm": -1
   },
   {
    "idJugador": "1541543",
    "titular": false,
    "dorsal": "50",
    "nombre": "DIAZ ALEJANO, JACOBO",
    "seg": 1173,
    "pt": 10,
    "t2": {
     "a": 2,
     "i": 3
    },
    "t3": {
     "a": 1,
     "i": 4
    },
    "tc": {
     "a": 3,
     "i": 7
    },
    "tl": {
     "a": 3,
     "i": 3
    },
    "ro": 1,
    "rd": 2,
    "rt": 3,
    "as": 1,
    "br": 0,
    "bp": 0,
    "tf": 0,
    "tco": 0,
    "mt": 0,
    "fc": 1,
    "fr": 2,
    "va": 11,
    "pm": 12
   }
  ],
  "visitante": [
   {
    "idJugador": "1878729",
    "titular": false,
    "dorsal": "0",
    "nombre": "GODSPOWER JOHNSON, JEFFREY ISIMA",
    "seg": 189,
    "pt": 0,
    "t2": {
     "a": 0,
     "i": 0
    },
    "t3": {
     "a": 0,
     "i": 1
    },
    "tc": {
     "a": 0,
     "i": 1
    },
    "tl": {
     "a": 0,
     "i": 0
    },
    "ro": 0,
    "rd": 0,
    "rt": 0,
    "as": 0,
    "br": 0,
    "bp": 0,
    "tf": 0,
    "tco": 0,
    "mt": 0,
    "fc": 0,
    "fr": 0,
    "va": -1,
    "pm": 1
   },
   {
    "idJugador": "2451278",
    "titular": false,
    "dorsal": "1",
    "nombre": "POIRIER, DAREL ALAN",
    "seg": 1203,
    "pt": 10,
    "t2": {
     "a": 2,
     "i": 4
    },
    "t3": {
     "a": 2,
     "i": 3
    },
    "tc": {
     "a": 4,
     "i": 7
    },
    "tl": {
     "a": 0,
     "i": 0
    },
    "ro": 0,
    "rd": 3,
    "rt": 3,
    "as": 1,
    "br": 0,
    "bp": 2,
    "tf": 0,
    "tco": 1,
    "mt": 1,
    "fc": 4,
    "fr": 0,
    "va": 5,
    "pm": -1
   },
   {
    "idJugador": "1890951",
    "titular": false,
    "dorsal": "4",
    "nombre": "PENO, STEFAN",
    "seg": 821,
    "pt": 3,
    "t2": {
     "a": 0,
     "i": 2
    },
    "t3": {
     "a": 1,
     "i": 2
    },
    "tc": {
     "a": 1,
     "i": 4
    },
    "tl": {
     "a": 0,
     "i": 0
    },
    "ro": 0,
    "rd": 0,
    "rt": 0,
    "as": 0,
    "br": 0,
    "bp": 3,
    "tf": 0,
    "tco": 0,
    "mt": 0,
    "fc": 2,
    "fr": 1,
    "va": -4,
    "pm": -12
   },
   {
    "idJugador": "2819191",
    "titular": false,
    "dorsal": "5",
    "nombre": "HERON, MUSTAPHA JAHHAD",
    "seg": 1317,
    "pt": 11,
    "t2": {
     "a": 2,
     "i": 3
    },
    "t3": {
     "a": 2,
     "i": 3
    },
    "tc": {
     "a": 4,
     "i": 6
    },
    "tl": {
     "a": 1,
     "i": 3
    },
    "ro": 1,
    "rd": 3,
    "rt": 4,
    "as": 0,
    "br": 2,
    "bp": 2,
    "tf": 0,
    "tco": 0,
    "mt": 0,
    "fc": 3,
    "fr": 5,
    "va": 13,
    "pm": -7
   },
   {
    "idJugador": "1677841",
    "titular": true,
    "dorsal": "7",
    "nombre": "CORDOBA MURO, PABLO",
    "seg": 1204,
    "pt": 8,
    "t2": {
     "a": 0,
     "i": 1
    },
    "t3": {
     "a": 2,
     "i": 5
    },
    "tc": {
     "a": 2,
     "i": 6
    },
    "tl": {
     "a": 2,
     "i": 2
    },
    "ro": 1,
    "rd": 2,
    "rt": 3,
    "as": 2,
    "br": 2,
    "bp": 1,
    "tf": 0,
    "tco": 0,
    "mt": 0,
    "fc": 3,
    "fr": 2,
    "va": 9,
    "pm": -10
   },
   {
    "idJugador": "2734873",
    "titular": true,
    "dorsal": "12",
    "nombre": "KRUTOUS, PAVLO",
    "seg": 1157,
    "pt": 3,
    "t2": {
     "a": 0,
     "i": 1
    },
    "t3": {
     "a": 1,
     "i": 1
    },
    "tc": {
     "a": 1,
     "i": 2
    },
    "tl": {
     "a": 0,
     "i": 0
    },
    "ro": 2,
    "rd": 1,
    "rt": 3,
    "as": 1,
    "br": 0,
    "bp": 1,
    "tf": 0,
    "tco": 0,
    "mt": 0,
    "fc": 1,
    "fr": 0,
    "va": 4,
    "pm": 5
   },
   {
    "idJugador": "2647156",
    "titular": true,
    "dorsal": "21",
    "nombre": "DEBAUT, LUDGY DOMINIQUE",
    "seg": 1197,
    "pt": 8,
    "t2": {
     "a": 4,
     "i": 7
    },
    "t3": {
     "a": 0,
     "i": 0
    },
    "tc": {
     "a": 4,
     "i": 7
    },
    "tl": {
     "a": 0,
     "i": 0
    },
    "ro": 6,
    "rd": 0,
    "rt": 6,
    "as": 1,
    "br": 1,
    "bp": 1,
    "tf": 0,
    "tco": 0,
    "mt": 2,
    "fc": 2,
    "fr": 0,
    "va": 10,
    "pm": -11
   },
   {
    "idJugador": "1251001",
    "titular": false,
    "dorsal": "22",
    "nombre": "DIAZ RODRIGUEZ, CRISTIAN",
    "seg": 933,
    "pt": 4,
    "t2": {
     "a": 2,
     "i": 4
    },
    "t3": {
     "a": 0,
     "i": 2
    },
    "tc": {
     "a": 2,
     "i": 6
    },
    "tl": {
     "a": 0,
     "i": 0
    },
    "ro": 1,
    "rd": 2,
    "rt": 3,
    "as": 1,
    "br": 2,
    "bp": 2,
    "tf": 0,
    "tco": 0,
    "mt": 0,
    "fc": 1,
    "fr": 2,
    "va": 5,
    "pm": -13
   },
   {
    "idJugador": "2739848",
    "titular": true,
    "dorsal": "23",
    "nombre": "STUMBRIS, ROBERTS",
    "seg": 1350,
    "pt": 8,
    "t2": {
     "a": 1,
     "i": 4
    },
    "t3": {
     "a": 2,
     "i": 5
    },
    "tc": {
     "a": 3,
     "i": 9
    },
    "tl": {
     "a": 0,
     "i": 0
    },
    "ro": 0,
    "rd": 2,
    "rt": 2,
    "as": 1,
    "br": 1,
    "bp": 1,
    "tf": 0,
    "tco": 0,
    "mt": 0,
    "fc": 2,
    "fr": 1,
    "va": 4,
    "pm": -15
   },
   {
    "idJugador": "2734242",
    "titular": false,
    "dorsal": "33",
    "nombre": "STILMA, MORGAN SIETSE",
    "seg": 1050,
    "pt": 12,
    "t2": {
     "a": 1,
     "i": 3
    },
    "t3": {
     "a": 2,
     "i": 6
    },
    "tc": {
     "a": 3,
     "i": 9
    },
    "tl": {
     "a": 4,
     "i": 4
    },
    "ro": 2,
    "rd": 4,
    "rt": 6,
    "as": 5,
    "br": 1,
    "bp": 2,
    "tf": 0,
    "tco": 1,
    "mt": 0,
    "fc": 3,
    "fr": 4,
    "va": 17,
    "pm": 3
   },
   {
    "idJugador": "1978541",
    "titular": true,
    "dorsal": "44",
    "nombre": "GARCIA SANCHEZ, JAVIER",
    "seg": 1579,
    "pt": 22,
    "t2": {
     "a": 5,
     "i": 5
    },
    "t3": {
     "a": 3,
     "i": 8
    },
    "tc": {
     "a": 8,
     "i": 13
    },
    "tl": {
     "a": 3,
     "i": 3
    },
    "ro": 0,
    "rd": 1,
    "rt": 1,
    "as": 6,
    "br": 0,
    "bp": 2,
    "tf": 0,
    "tco": 0,
    "mt": 0,
    "fc": 2,
    "fr": 2,
    "va": 22,
    "pm": 0
   }
  ],
  "cuartos": [
   {
    "periodo": "1º C",
    "local": 25,
    "visitante": 22
   },
   {
    "periodo": "2º C",
    "local": 27,
    "visitante": 20
   },
   {
    "periodo": "3º C",
    "local": 21,
    "visitante": 26
   },
   {
    "periodo": "4º C",
    "local": 28,
    "visitante": 21
   }
  ]
 }
}