{
 "id": "2486859",
 "temporada": "2025",
 "competicion": "segundafeb",
 "grupo": "ESTE",
 "jornada": "Jornada 2(11/10/2025)",
 "equipoLocal": {
  "id": "981207",
  "nombre": "OCA GLOBAL C.B. SALOU"
 },
 "equipoVisitante": {
  "id": "981490",
  "nombre": "CLUB ESPORTIU BÀSQUET LLÍRIA"
 },
 "resultado": "57-68",
 "disputado": true,
 "descargado": "2026-07-20T13:38:17.009Z",
 "boxscore": {
  "local": [
   {
    "idJugador": "2715040",
    "titular": true,
    "dorsal": "3",
    "nombre": "TRAORE, BREHIMA SEYDOU",
    "seg": 1303,
    "pt": 4,
    "t2": {
     "a": 2,
     "i": 4
    },
    "t3": {
     "a": 0,
     "i": 4
    },
    "tc": {
     "a": 2,
     "i": 8
    },
    "tl": {
     "a": 0,
     "i": 1
    },
    "ro": 3,
    "rd": 5,
    "rt": 8,
    "as": 1,
    "br": 1,
    "bp": 2,
    "tf": 0,
    "tco": 0,
    "mt": 0,
    "fc": 3,
    "fr": 3,
    "va": 5,
    "pm": -10
   },
   {
    "idJugador": "1271466",
    "titular": true,
    "dorsal": "4",
    "nombre": "CUELLAR GARCIA, DAVID",
    "seg": 2053,
    "pt": 4,
    "t2": {
     "a": 0,
     "i": 2
    },
    "t3": {
     "a": 1,
     "i": 4
    },
    "tc": {
     "a": 1,
     "i": 6
    },
    "tl": {
     "a": 1,
     "i": 2
    },
    "ro": 0,
    "rd": 8,
    "rt": 8,
    "as": 5,
    "br": 2,
    "bp": 0,
    "tf": 0,
    "tco": 0,
    "mt": 0,
    "fc": 2,
    "fr": 5,
    "va": 16,
    "pm": -10
   },
   {
    "idJugador": "2242531",
    "titular": true,
    "dorsal": "5",
    "nombre": "MOURE COLOMBO, EDGAR",
    "seg": 816,
    "pt": 6,
    "t2": {
     "a": 3,
     "i": 7
    },
    "t3": {
     "a": 0,
     "i": 1
    },
    "tc": {
     "a": 3,
     "i": 8
    },
    "tl": {
     "a": 0,
     "i": 1
    },
    "ro": 1,
    "rd": 0,
    "rt": 1,
    "as": 1,
    "br": 1,
    "bp": 1,
    "tf": 0,
    "tco": 0,
    "mt": 0,
    "fc": 2,
    "fr": 1,
    "va": 1,
    "pm": -5
   },
   {
    "idJugador": "1967605",
    "titular": false,
    "dorsal": "9",
    "nombre": "SIMS SERRA, EDDY",
    "seg": 475,
    "pt": 0,
    "t2": {
     "a": 0,
     "i": 0
    },
    "t3": {
     "a": 0,
     "i": 1
    },
    "tc": {
     "a": 0,
     "i": 1
    },
    "tl": {
     "a": 0,
     "i": 0
    },
    "ro": 0,
    "rd": 0,
    "rt": 0,
    "as": 0,
    "br": 0,
    "bp": 1,
    "tf": 0,
    "tco": 0,
    "mt": 0,
    "fc": 2,
    "fr": 0,
    "va": -4,
    "pm": -7
   },
   {
    "idJugador": "2825543",
    "titular": true,
    "dorsal": "11",
    "nombre": "JACKSON, DARIEN",
    "seg": 1925,
    "pt": 8,
    "t2": {
     "a": 1,
     "i": 5
    },
    "t3": {
     "a": 2,
     "i": 2
    },
    "tc": {
     "a": 3,
     "i": 7
    },
    "tl": {
     "a": 0,
     "i": 0
    },
    "ro": 1,
    "rd": 1,
    "rt": 2,
    "as": 7,
    "br": 2,
    "bp": 3,
    "tf": 0,
    "tco": 1,
    "mt": 0,
    "fc": 2,
    "fr": 2,
    "va": 12,
    "pm": -4
   },
   {
    "idJugador": "2790712",
    "titular": false,
    "dorsal": "13",
    "nombre": "CAJELLI TRIVER, JUAN MARTIN",
    "seg": 234,
    "pt": 0,
    "t2": {
     "a": 0,
     "i": 0
    },
    "t3": {
     "a": 0,
     "i": 0
    },
    "tc": {
     "a": 0,
     "i": 0
    },
    "tl": {
     "a": 0,
     "i": 0
    },
    "ro": 0,
    "rd": 0,
    "rt": 0,
    "as": 0,
    "br": 0,
    "bp": 0,
    "tf": 0,
    "tco": 0,
    "mt": 0,
    "fc": 3,
    "fr": 0,
    "va": -3,
    "pm": 2
   },
   {
    "idJugador": "2274746",
    "titular": false,
    "dorsal": "17",
    "nombre": "SALO BLAYA, POL",
    "seg": 592,
    "pt": 6,
    "t2": {
     "a": 3,
     "i": 5
    },
    "t3": {
     "a": 0,
     "i": 0
    },
    "tc": {
     "a": 3,
     "i": 5
    },
    "tl": {
     "a": 0,
     "i": 0
    },
    "ro": 1,
    "rd": 0,
    "rt": 1,
    "as": 0,
    "br": 0,
    "bp": 1,
    "tf": 0,
    "tco": 0,
    "mt": 0,
    "fc": 3,
    "fr": 0,
    "va": 1,
    "pm": -2
   },
   {
    "idJugador": "2534398",
    "titular": false,
    "dorsal": "22",
    "nombre": "SÁNCHEZ, JOAQUIN",
    "seg": 1584,
    "pt": 10,
    "t2": {
     "a": 1,
     "i": 5
    },
    "t3": {
     "a": 2,
     "i": 6
    },
    "tc": {
     "a": 3,
     "i": 11
    },
    "tl": {
     "a": 2,
     "i": 2
    },
    "ro": 2,
    "rd": 5,
    "rt": 7,
    "as": 0,
    "br": 0,
    "bp": 5,
    "tf": 0,
    "tco": 1,
    "mt": 0,
    "fc": 2,
    "fr": 4,
    "va": 6,
    "pm": -6
   },
   {
    "idJugador": "1438515",
    "titular": false,
    "dorsal": "33",
    "nombre": "MORALES ROS, ANTONIO JOSE",
    "seg": 1675,
    "pt": 13,
    "t2": {
     "a": 4,
     "i": 6
    },
    "t3": {
     "a": 1,
     "i": 8
    },
    "tc": {
     "a": 5,
     "i": 14
    },
    "tl": {
     "a": 2,
     "i": 2
    },
    "ro": 2,
    "rd": 4,
    "rt": 6,
    "as": 0,
    "br": 2,
    "bp": 1,
    "tf": 0,
    "tco": 0,
    "mt": 1,
    "fc": 2,
    "fr": 2,
    "va": 11,
    "pm": -7
   },
   {
    "idJugador": "2827753",
    "titular": true,
    "dorsal": "70",
    "nombre": "OKENCHI, OBUMNEME ERIC",
    "seg": 1343,
    "pt": 6,
    "t2": {
     "a": 3,
     "i": 6
    },
    "t3": {
     "a": 0,
     "i": 0
    },
    "tc": {
     "a": 3,
     "i": 6
    },
    "tl": {
     "a": 0,
     "i": 2
    },
    "ro": 0,
    "rd": 2,
    "rt": 2,
    "as": 1,
    "br": 1,
    "bp": 4,
    "tf": 0,
    "tco": 0,
    "mt": 0,
    "fc": 5,
    "fr": 5,
    "va": 1,
    "pm": -6
   }
  ],
  "visitante": [
   {
    "idJugador": "2274877",
    "titular": false,
    "dorsal": "0",
    "nombre": "CLEMENT AIGBOGUN, KENNEDY OSARIEMEN",
    "seg": 935,
    "pt": 9,
    "t2": {
     "a": 4,
     "i": 5
    },
    "t3": {
     "a": 0,
     "i": 5
    },
    "tc": {
     "a": 4,
     "i": 10
    },
    "tl": {
     "a": 1,
     "i": 3
    },
    "ro": 2,
    "rd": 2,
    "rt": 4,
    "as": 0,
    "br": 0,
    "bp": 0,
    "tf": 0,
    "tco": 0,
    "mt": 3,
    "fc": 0,
    "fr": 3,
    "va": 8,
    "pm": 0
   },
   {
    "idJugador": "2665346",
    "titular": true,
    "dorsal": "2",
    "nombre": "KANDULU, DOUGLAS",
    "seg": 723,
    "pt": 5,
    "t2": {
     "a": 2,
     "i": 2
    },
    "t3": {
     "a": 0,
     "i": 0
    },
    "tc": {
     "a": 2,
     "i": 2
    },
    "tl": {
     "a": 1,
     "i": 2
    },
    "ro": 1,
    "rd": 1,
    "rt": 2,
    "as": 0,
    "br": 1,
    "bp": 3,
    "tf": 0,
    "tco": 0,
    "mt": 1,
    "fc": 5,
    "fr": 3,
    "va": 2,
    "pm": 0
   },
   {
    "idJugador": "1702333",
    "titular": false,
    "dorsal": "3",
    "nombre": "HERRERA SAURET, EZEQUIEL",
    "seg": 1053,
    "pt": 5,
    "t2": {
     "a": 1,
     "i": 3
    },
    "t3": {
     "a": 1,
     "i": 4
    },
    "tc": {
     "a": 2,
     "i": 7
    },
    "tl": {
     "a": 0,
     "i": 0
    },
    "ro": 0,
    "rd": 2,
    "rt": 2,
    "as": 5,
    "br": 1,
    "bp": 1,
    "tf": 0,
    "tco": 0,
    "mt": 0,
    "fc": 3,
    "fr": 2,
    "va": 6,
    "pm": 7
   },
   {
    "idJugador": "1995160",
    "titular": true,
    "dorsal": "5",
    "nombre": "RIVAS PALMER, DIEGO",
    "seg": 1454,
    "pt": 8,
    "t2": {
     "a": 0,
     "i": 1
    },
    "t3": {
     "a": 2,
     "i": 5
    },
    "tc": {
     "a": 2,
     "i": 6
    },
    "tl": {
     "a": 2,
     "i": 2
    },
    "ro": 2,
    "rd": 1,
    "rt": 3,
    "as": 0,
    "br": 0,
    "bp": 2,
    "tf": 0,
    "tco": 0,
    "mt": 0,
    "fc": 2,
    "fr": 2,
    "va": 5,
    "pm": 10
   },
   {
    "idJugador": "1882178",
    "titular": false,
    "dorsal": "7",
    "nombre": "PALAMOS MOLINS, JAIME",
    "seg": 1057,
    "pt": 9,
    "t2": {
     "a": 2,
     "i": 2
    },
    "t3": {
     "a": 1,
     "i": 1
    },
    "tc": {
     "a": 3,
     "i": 3
    },
    "tl": {
     "a": 2,
     "i": 2
    },
    "ro": 0,
    "rd": 2,
    "rt": 2,
    "as": 2,
    "br": 2,
    "bp": 3,
    "tf": 0,
    "tco": 0,
    "mt": 0,
    "fc": 3,
    "fr": 4,
    "va": 13,
    "pm": 1
   },
   {
    "idJugador": "2281145",
    "titular": true,
    "dorsal": "8",
    "nombre": "RIVAS PALMER, ALEJANDRO",
    "seg": 1604,
    "pt": 9,
    "t2": {
     "a": 3,
     "i": 5
    },
    "t3": {
     "a": 1,
     "i": 5
    },
    "tc": {
     "a": 4,
     "i": 10
    },
    "tl": {
     "a": 0,
     "i": 0
    },
    "ro": 1,
    "rd": 6,
    "rt": 7,
    "as": 0,
    "br": 0,
    "bp": 2,
    "tf": 0,
    "tco": 0,
    "mt": 0,
    "fc": 1,
    "fr": 1,
    "va": 8,
    "pm": 5
   },
   {
    "idJugador": "1560358",
    "titular": true,
    "dorsal": "12",
    "nombre": "MEANA PEREZ, ALONSO",
    "seg": 1343,
    "pt": 10,
    "t2": {
     "a": 2,
     "i": 6
    },
    "t3": {
     "a": 0,
     "i": 0
    },
    "tc": {
     "a": 2,
     "i": 6
    },
    "tl": {
     "a": 6,
     "i": 8
    },
    "ro": 0,
    "rd": 4,
    "rt": 4,
    "as": 4,
    "br": 0,
    "bp": 2,
    "tf": 0,
    "tco": 0,
    "mt": 0,
    "fc": 1,
    "fr": 7,
    "va": 16,
    "pm": 10
   },
   {
    "idJugador": "1257494",
    "titular": false,
    "dorsal": "13",
    "nombre": "PEREZ TOMAS, VICTOR",
    "seg": 890,
    "pt": 0,
    "t2": {
     "a": 0,
     "i": 0
    },
    "t3": {
     "a": 0,
     "i": 5
    },
    "tc": {
     "a": 0,
     "i": 5
    },
    "tl": {
     "a": 0,
     "i": 0
    },
    "ro": 0,
    "rd": 1,
    "rt": 1,
    "as": 0,
    "br": 1,
    "bp": 1,
    "tf": 0,
    "tco": 0,
    "mt": 0,
    "fc": 0,
    "fr": 0,
    "va": -4,
    "pm": -2
   },
   {
    "idJugador": "1761293",
    "titular": false,
    "dorsal": "16",
    "nombre": "BONO SOLER, PABLO",
    "seg": 879,
    "pt": 0,
    "t2": {
     "a": 0,
     "i": 2
    },
    "t3": {
     "a": 0,
     "i": 0
    },
    "tc": {
     "a": 0,
     "i": 2
    },
    "tl": {
     "a": 0,
     "i": 0
    },
    "ro": 0,
    "rd": 1,
    "rt": 1,
    "as": 2,
    "br": 0,
    "bp": 0,
    "tf": 0,
    "tco": 0,
    "mt": 0,
    "fc": 1,
    "fr": 1,
    "va": 1,
    "pm": 13
   },
   {
    "idJugador": "2184821",
    "titular": false,
    "dorsal": "18",
    "nombre": "ENABULELE OGUNSUYI, MICHAEL",
    "seg": 1119,
    "pt": 4,
    "t2": {
     "a": 2,
     "i": 3
    },
    "t3": {
     "a": 0,
     "i": 0
    },
    "tc": {
     "a": 2,
     "i": 3
    },
    "tl": {
     "a": 0,
     "i": 2
    },
    "ro": 1,
    "rd": 2,
    "rt": 3,
    "as": 0,
    "br": 0,
    "bp": 1,
    "tf": 1,
    "tco": 0,
    "mt": 1,
    "fc": 3,
    "fr": 1,
    "va": 2,
    "pm": 3
   },
   {
    "idJugador": "2164761",
    "titular": false,
    "dorsal": "28",
    "nombre": "NAVARRO MALDONADO, PAU",
    "seg": 64,
    "pt": 0,
    "t2": {
     "a": 0,
     "i": 0
    },
    "t3": {
     "a": 0,
     "i": 0
    },
    "tc": {
     "a": 0,
     "i": 0
    },
    "tl": {
     "a": 0,
     "i": 0
    },
    "ro": 0,
    "rd": 0,
    "rt": 0,
    "as": 0,
    "br": 0,
    "bp": 0,
    "tf": 0,
    "tco": 0,
    "mt": 0,
    "fc": 0,
    "fr": 0,
    "va": 0,
    "pm": -3
   },
   {
    "idJugador": "2222436",
    "titular": true,
    "dorsal": "30",
    "nombre": "GALLEGO MOGRO, SALVADOR",
    "seg": 879,
    "pt": 9,
    "t2": {
     "a": 1,
     "i": 1
    },
    "t3": {
     "a": 1,
     "i": 1
    },
    "tc": {
     "a": 2,
     "i": 2
    },
    "tl": {
     "a": 4,
     "i": 4
    },
    "ro": 1,
    "rd": 5,
    "rt": 6,
    "as": 0,
    "br": 0,
    "bp": 1,
    "tf": 1,
    "tco": 0,
    "mt": 0,
    "fc": 3,
    "fr": 2,
    "va": 14,
    "pm": 11
   }
  ],
  "cuartos": [
   {
    "periodo": "1º C",
    "local": 19,
    "visitante": 22
   },
   {
    "periodo": "2º C",
    "local": 9,
    "visitante": 17
   },
   {
    "periodo": "3º C",
    "local": 9,
    "visitante": 13
   },
   {
    "periodo": "4º C",
    "local": 20,
    "visitante": 16
   }
  ]
 }
}