{
 "id": "2341487",
 "temporada": "2023",
 "competicion": "primerafeb",
 "grupo": "UNICO",
 "jornada": "Jornada 4(27/10/2023)",
 "equipoLocal": {
  "id": "922724",
  "nombre": "MELILLA CIUDAD DEL DEPORTE"
 },
 "equipoVisitante": {
  "id": "921517",
  "nombre": "REAL BETIS BALONCESTO"
 },
 "resultado": "83-87",
 "disputado": true,
 "descargado": "2026-07-21T06:26:32.101Z",
 "boxscore": {
  "local": [
   {
    "idJugador": "2647445",
    "titular": false,
    "dorsal": "1",
    "nombre": "MARJANOVIC, ANDRIJA",
    "seg": 1769,
    "pt": 8,
    "t2": {
     "a": 1,
     "i": 2
    },
    "t3": {
     "a": 2,
     "i": 3
    },
    "tc": {
     "a": 3,
     "i": 5
    },
    "tl": {
     "a": 0,
     "i": 0
    },
    "ro": 1,
    "rd": 3,
    "rt": 4,
    "as": 0,
    "br": 1,
    "bp": 1,
    "tf": 0,
    "tco": 1,
    "mt": 0,
    "fc": 0,
    "fr": 0,
    "va": 10,
    "pm": 2
   },
   {
    "idJugador": "1756469",
    "titular": false,
    "dorsal": "5",
    "nombre": "FIGUEROA ÁLVAREZ, HÉCTOR",
    "seg": 700,
    "pt": 8,
    "t2": {
     "a": 1,
     "i": 2
    },
    "t3": {
     "a": 2,
     "i": 3
    },
    "tc": {
     "a": 3,
     "i": 5
    },
    "tl": {
     "a": 0,
     "i": 0
    },
    "ro": 2,
    "rd": 2,
    "rt": 4,
    "as": 1,
    "br": 0,
    "bp": 0,
    "tf": 0,
    "tco": 0,
    "mt": 0,
    "fc": 2,
    "fr": 1,
    "va": 10,
    "pm": 8
   },
   {
    "idJugador": "2647409",
    "titular": true,
    "dorsal": "7",
    "nombre": "VAN DYKE, PARKER DERRAH",
    "seg": 1894,
    "pt": 17,
    "t2": {
     "a": 1,
     "i": 3
    },
    "t3": {
     "a": 5,
     "i": 10
    },
    "tc": {
     "a": 6,
     "i": 13
    },
    "tl": {
     "a": 0,
     "i": 0
    },
    "ro": 0,
    "rd": 1,
    "rt": 1,
    "as": 3,
    "br": 0,
    "bp": 2,
    "tf": 1,
    "tco": 0,
    "mt": 0,
    "fc": 4,
    "fr": 1,
    "va": 10,
    "pm": -2
   },
   {
    "idJugador": "2433575",
    "titular": false,
    "dorsal": "8",
    "nombre": "LEPICHEV, SIMEON IVANOV",
    "seg": 955,
    "pt": 10,
    "t2": {
     "a": 3,
     "i": 4
    },
    "t3": {
     "a": 0,
     "i": 0
    },
    "tc": {
     "a": 3,
     "i": 4
    },
    "tl": {
     "a": 4,
     "i": 4
    },
    "ro": 1,
    "rd": 3,
    "rt": 4,
    "as": 1,
    "br": 0,
    "bp": 0,
    "tf": 0,
    "tco": 0,
    "mt": 0,
    "fc": 3,
    "fr": 4,
    "va": 15,
    "pm": -10
   },
   {
    "idJugador": "1794663",
    "titular": true,
    "dorsal": "9",
    "nombre": "ARCOS GONZALEZ, GUILLEM",
    "seg": 1402,
    "pt": 4,
    "t2": {
     "a": 1,
     "i": 1
    },
    "t3": {
     "a": 0,
     "i": 4
    },
    "tc": {
     "a": 1,
     "i": 5
    },
    "tl": {
     "a": 2,
     "i": 2
    },
    "ro": 0,
    "rd": 2,
    "rt": 2,
    "as": 6,
    "br": 0,
    "bp": 1,
    "tf": 0,
    "tco": 0,
    "mt": 0,
    "fc": 1,
    "fr": 4,
    "va": 10,
    "pm": -6
   },
   {
    "idJugador": "1674978",
    "titular": false,
    "dorsal": "10",
    "nombre": "MULERO MALDONADO, GUILLERMO",
    "seg": 163,
    "pt": 0,
    "t2": {
     "a": 0,
     "i": 0
    },
    "t3": {
     "a": 0,
     "i": 0
    },
    "tc": {
     "a": 0,
     "i": 0
    },
    "tl": {
     "a": 0,
     "i": 0
    },
    "ro": 0,
    "rd": 0,
    "rt": 0,
    "as": 0,
    "br": 0,
    "bp": 0,
    "tf": 0,
    "tco": 0,
    "mt": 0,
    "fc": 0,
    "fr": 0,
    "va": 0,
    "pm": 0
   },
   {
    "idJugador": "2647413",
    "titular": false,
    "dorsal": "11",
    "nombre": "RICHMOND, RYAN TIMOTHY",
    "seg": 298,
    "pt": 3,
    "t2": {
     "a": 1,
     "i": 1
    },
    "t3": {
     "a": 0,
     "i": 2
    },
    "tc": {
     "a": 1,
     "i": 3
    },
    "tl": {
     "a": 1,
     "i": 2
    },
    "ro": 0,
    "rd": 0,
    "rt": 0,
    "as": 1,
    "br": 0,
    "bp": 0,
    "tf": 0,
    "tco": 0,
    "mt": 0,
    "fc": 0,
    "fr": 2,
    "va": 3,
    "pm": -6
   },
   {
    "idJugador": "1763780",
    "titular": false,
    "dorsal": "12",
    "nombre": "MENENDEZ GARCIA, JAVIER",
    "seg": 499,
    "pt": 4,
    "t2": {
     "a": 2,
     "i": 2
    },
    "t3": {
     "a": 0,
     "i": 0
    },
    "tc": {
     "a": 2,
     "i": 2
    },
    "tl": {
     "a": 0,
     "i": 0
    },
    "ro": 0,
    "rd": 1,
    "rt": 1,
    "as": 0,
    "br": 0,
    "bp": 0,
    "tf": 1,
    "tco": 0,
    "mt": 0,
    "fc": 3,
    "fr": 0,
    "va": 3,
    "pm": 6
   },
   {
    "idJugador": "2647436",
    "titular": false,
    "dorsal": "31",
    "nombre": "GADILIAUSKAS, ROKAS",
    "seg": 10,
    "pt": 0,
    "t2": {
     "a": 0,
     "i": 0
    },
    "t3": {
     "a": 0,
     "i": 0
    },
    "tc": {
     "a": 0,
     "i": 0
    },
    "tl": {
     "a": 0,
     "i": 0
    },
    "ro": 0,
    "rd": 0,
    "rt": 0,
    "as": 0,
    "br": 0,
    "bp": 0,
    "tf": 0,
    "tco": 0,
    "mt": 0,
    "fc": 1,
    "fr": 0,
    "va": -1,
    "pm": 0
   },
   {
    "idJugador": "2647411",
    "titular": true,
    "dorsal": "44",
    "nombre": "VARENCE, HASAN SHAKUR",
    "seg": 1808,
    "pt": 12,
    "t2": {
     "a": 4,
     "i": 5
    },
    "t3": {
     "a": 1,
     "i": 7
    },
    "tc": {
     "a": 5,
     "i": 12
    },
    "tl": {
     "a": 1,
     "i": 2
    },
    "ro": 1,
    "rd": 11,
    "rt": 12,
    "as": 1,
    "br": 2,
    "bp": 2,
    "tf": 0,
    "tco": 1,
    "mt": 2,
    "fc": 2,
    "fr": 1,
    "va": 16,
    "pm": -5
   },
   {
    "idJugador": "2647555",
    "titular": true,
    "dorsal": "55",
    "nombre": "TAMULIS, JUSTAS",
    "seg": 1007,
    "pt": 2,
    "t2": {
     "a": 1,
     "i": 1
    },
    "t3": {
     "a": 0,
     "i": 3
    },
    "tc": {
     "a": 1,
     "i": 4
    },
    "tl": {
     "a": 0,
     "i": 0
    },
    "ro": 0,
    "rd": 0,
    "rt": 0,
    "as": 2,
    "br": 0,
    "bp": 1,
    "tf": 0,
    "tco": 0,
    "mt": 0,
    "fc": 1,
    "fr": 0,
    "va": -1,
    "pm": -6
   }
  ],
  "visitante": [
   {
    "idJugador": "2670349",
    "titular": false,
    "dorsal": "2",
    "nombre": "BARNES, JORDAN LIVINGSTON",
    "seg": 871,
    "pt": 2,
    "t2": {
     "a": 1,
     "i": 3
    },
    "t3": {
     "a": 0,
     "i": 2
    },
    "tc": {
     "a": 1,
     "i": 5
    },
    "tl": {
     "a": 0,
     "i": 0
    },
    "ro": 0,
    "rd": 1,
    "rt": 1,
    "as": 4,
    "br": 1,
    "bp": 1,
    "tf": 0,
    "tco": 1,
    "mt": 0,
    "fc": 3,
    "fr": 0,
    "va": 0,
    "pm": 5
   },
   {
    "idJugador": "2675260",
    "titular": false,
    "dorsal": "4",
    "nombre": "POLANCO TAVAREZ, EDDY RAFAEL",
    "seg": 1594,
    "pt": 14,
    "t2": {
     "a": 1,
     "i": 2
    },
    "t3": {
     "a": 2,
     "i": 4
    },
    "tc": {
     "a": 3,
     "i": 6
    },
    "tl": {
     "a": 6,
     "i": 8
    },
    "ro": 0,
    "rd": 1,
    "rt": 1,
    "as": 1,
    "br": 0,
    "bp": 0,
    "tf": 0,
    "tco": 0,
    "mt": 0,
    "fc": 1,
    "fr": 6,
    "va": 16,
    "pm": 5
   },
   {
    "idJugador": "2678649",
    "titular": true,
    "dorsal": "8",
    "nombre": "HANZLIK, ONDREJ",
    "seg": 1505,
    "pt": 4,
    "t2": {
     "a": 0,
     "i": 1
    },
    "t3": {
     "a": 1,
     "i": 5
    },
    "tc": {
     "a": 1,
     "i": 6
    },
    "tl": {
     "a": 1,
     "i": 2
    },
    "ro": 0,
    "rd": 8,
    "rt": 8,
    "as": 1,
    "br": 1,
    "bp": 0,
    "tf": 0,
    "tco": 0,
    "mt": 0,
    "fc": 1,
    "fr": 1,
    "va": 8,
    "pm": 6
   },
   {
    "idJugador": "1923881",
    "titular": false,
    "dorsal": "12",
    "nombre": "DOMENECH FONTANA, ADRIA",
    "seg": 900,
    "pt": 9,
    "t2": {
     "a": 3,
     "i": 3
    },
    "t3": {
     "a": 1,
     "i": 1
    },
    "tc": {
     "a": 4,
     "i": 4
    },
    "tl": {
     "a": 0,
     "i": 0
    },
    "ro": 1,
    "rd": 2,
    "rt": 3,
    "as": 0,
    "br": 2,
    "bp": 0,
    "tf": 0,
    "tco": 0,
    "mt": 1,
    "fc": 3,
    "fr": 0,
    "va": 11,
    "pm": 2
   },
   {
    "idJugador": "2816383",
    "titular": false,
    "dorsal": "16",
    "nombre": "DEDOVIC, NEDIM",
    "seg": 776,
    "pt": 0,
    "t2": {
     "a": 0,
     "i": 0
    },
    "t3": {
     "a": 0,
     "i": 1
    },
    "tc": {
     "a": 0,
     "i": 1
    },
    "tl": {
     "a": 0,
     "i": 0
    },
    "ro": 0,
    "rd": 2,
    "rt": 2,
    "as": 1,
    "br": 0,
    "bp": 2,
    "tf": 2,
    "tco": 1,
    "mt": 0,
    "fc": 1,
    "fr": 0,
    "va": 1,
    "pm": 6
   },
   {
    "idJugador": "2656128",
    "titular": true,
    "dorsal": "19",
    "nombre": "ROGIC, ROKO",
    "seg": 1701,
    "pt": 20,
    "t2": {
     "a": 6,
     "i": 8
    },
    "t3": {
     "a": 1,
     "i": 1
    },
    "tc": {
     "a": 7,
     "i": 9
    },
    "tl": {
     "a": 5,
     "i": 5
    },
    "ro": 0,
    "rd": 2,
    "rt": 2,
    "as": 7,
    "br": 0,
    "bp": 1,
    "tf": 0,
    "tco": 1,
    "mt": 0,
    "fc": 2,
    "fr": 7,
    "va": 31,
    "pm": 3
   },
   {
    "idJugador": "1512091",
    "titular": true,
    "dorsal": "22",
    "nombre": "RAKOCEVIC, NIKOLA",
    "seg": 1529,
    "pt": 13,
    "t2": {
     "a": 1,
     "i": 3
    },
    "t3": {
     "a": 3,
     "i": 7
    },
    "tc": {
     "a": 4,
     "i": 10
    },
    "tl": {
     "a": 2,
     "i": 2
    },
    "ro": 0,
    "rd": 3,
    "rt": 3,
    "as": 2,
    "br": 1,
    "bp": 0,
    "tf": 0,
    "tco": 1,
    "mt": 0,
    "fc": 2,
    "fr": 3,
    "va": 14,
    "pm": -7
   },
   {
    "idJugador": "2656525",
    "titular": true,
    "dorsal": "28",
    "nombre": "ROMERO FERNANDEZ, ISMAEL",
    "seg": 1588,
    "pt": 13,
    "t2": {
     "a": 6,
     "i": 9
    },
    "t3": {
     "a": 0,
     "i": 0
    },
    "tc": {
     "a": 6,
     "i": 9
    },
    "tl": {
     "a": 1,
     "i": 6
    },
    "ro": 4,
    "rd": 3,
    "rt": 7,
    "as": 1,
    "br": 0,
    "bp": 1,
    "tf": 0,
    "tco": 1,
    "mt": 1,
    "fc": 3,
    "fr": 3,
    "va": 12,
    "pm": -4
   },
   {
    "idJugador": "1877088",
    "titular": true,
    "dorsal": "33",
    "nombre": "KUKSIKS, RIHARDS",
    "seg": 1536,
    "pt": 12,
    "t2": {
     "a": 3,
     "i": 3
    },
    "t3": {
     "a": 2,
     "i": 9
    },
    "tc": {
     "a": 5,
     "i": 12
    },
    "tl": {
     "a": 0,
     "i": 0
    },
    "ro": 1,
    "rd": 1,
    "rt": 2,
    "as": 1,
    "br": 1,
    "bp": 0,
    "tf": 0,
    "tco": 0,
    "mt": 0,
    "fc": 1,
    "fr": 0,
    "va": 8,
    "pm": 4
   }
  ],
  "cuartos": [
   {
    "periodo": "1º C",
    "local": 19,
    "visitante": 29
   },
   {
    "periodo": "2º C",
    "local": 16,
    "visitante": 19
   },
   {
    "periodo": "3º C",
    "local": 23,
    "visitante": 19
   },
   {
    "periodo": "4º C",
    "local": 25,
    "visitante": 20
   }
  ]
 }
}